<?xml version="1.0"?>
<!DOCTYPE hibernate-mapping PUBLIC "-//Hibernate/Hibernate Mapping DTD 3.0//EN"
        "http://hibernate.sourceforge.net/hibernate-mapping-3.0.dtd">

<hibernate-mapping>
    <class name="hibernate.Usuario" table="usuario">

        <id name="id" type="java.lang.Integer" column="ID">
            <generator class="identity" />
        </id>

        <property name="nombre" column="nombre"/>
        <property name="apellido" column="apellido"/>
        <property name="dni" column="dni" unique="true"/>

    </class>
</hibernate-mapping>